livelossplot/__init__.py
livelossplot/main_logger.py
livelossplot/plot_losses.py
livelossplot/version.py
livelossplot/inputs/__init__.py
livelossplot/inputs/generic_keras.py
livelossplot/inputs/keras.py
livelossplot/inputs/poutyne.py
livelossplot/inputs/pytorch_ignite.py
livelossplot/inputs/tf_keras.py
livelossplot/outputs/__init__.py
livelossplot/outputs/base_output.py
livelossplot/outputs/bokeh_plot.py
livelossplot/outputs/extrema_printer.py
livelossplot/outputs/matplotlib_plot.py
livelossplot/outputs/matplotlib_subplots.py
livelossplot/outputs/neptune_logger.py
livelossplot/outputs/tensorboard_logger.py
livelossplot/outputs/tensorboard_tf_logger.py
realtimeplt-0.0.1.dist-info/LICENSE.txt
realtimeplt-0.0.1.dist-info/METADATA
realtimeplt-0.0.1.dist-info/WHEEL
realtimeplt-0.0.1.dist-info/top_level.txt
realtimeplt-0.0.1.dist-info/RECORD
