Metadata-Version: 2.1
Name: realtimeplt
Version: 0.0.1
Summary: Realtime plot of loss plot in Jupyter Notebook for Keras, PyTorch and others.
Home-page: UNKNOWN
Author: Aryan Karn
Author-email: aryankarnin@gmail.com
License: MIT
Keywords: keras,pytorch,plot,chart,deep-learning
Platform: UNKNOWN
Classifier: Development Status :: 4 - Beta
Classifier: Framework :: Jupyter
Classifier: Intended Audience :: Developers
Classifier: Intended Audience :: Education
Classifier: Intended Audience :: Science/Research
Classifier: Topic :: Scientific/Engineering :: Artificial Intelligence
Classifier: Topic :: Scientific/Engineering :: Visualization
Classifier: License :: OSI Approved :: MIT License
Classifier: Programming Language :: Python :: 3.5
Classifier: Programming Language :: Python :: 3.6
Classifier: Programming Language :: Python :: 3.7
Classifier: Programming Language :: Python :: 3.8
Requires-Python: >3.5
Requires-Dist: ipython
Requires-Dist: matplotlib (<3.1) ; python_version < "3.6"
Requires-Dist: numpy (<1.18) ; python_version < "3.6"
Requires-Dist: bokeh (<=1.4.0) ; python_version < "3.6"
Requires-Dist: matplotlib ; python_version >= "3.6"
Requires-Dist: bokeh ; python_version >= "3.6"
